Workbook
Name Slicer_Region: #N/A

Sheet Cover Page
C3: Dashboard Dataset
C7: Get 10% OFF our course using coupon code EMAIL10
C9: Get our Excel for Business and Finance course.
C11: Made by Career Principles Ltd.
C13: Note
C14: All content is copyright material of Career Principles Ltd.
C15: This Excel model may not be reproduced or distributed by any means, including printing, screencapturing, or any other method without the prior permission of the publisher.

Sheet Analysis
A3: Sum of Total Sales | B3: Sum of Units Sold | C3: Average of Price per Unit | D3: Sum of Operating Profit
A4: 12016665 | B4: 24788610 | C4: 0.45216625 | D4: 4722496.8
A7: Sum of Total Sales | B7: Column Labels
A8: Row Labels | B8: 2022 | C8: 2023 | D8: Grand Total
A9: Coca-Cola | B9: 499102 | C9: 2268974.9 | D9: 2768076.9
A10: Dasani Water | B10: 469270.7 | C10: 1917827.8 | D10: 2387098.5
A11: Diet Coke | B11: 423758.7 | C11: 1633959.3 | D11: 2057718
A12: Fanta | B12: 315489.2 | C12: 1116062.9 | D12: 1431552.1
A13: Powerade | B13: 349533.9 | C13: 1302529.3 | D13: 1652063.2
A14: Sprite | B14: 366578 | C14: 1353578.3 | D14: 1720156.3
A15: Grand Total | B15: 2423732.5 | C15: 9592932.5 | D15: 12016665
A18: Years (Invoice Date) | B18: Quarters (Invoice Date) | C18: Sum of Total Sales | D18: Average of Operating Margin
A19: 2022 | B19: Qtr1 | C19: 692776.1 | D19: 0.40174684 | E19: =A19 -> 2022 | F19: =B19 -> Qtr1 | G19: =C19 -> 692776.1 | H19: =D19 -> 0.40174684
B20: Qtr2 | C20: 644203.9 | D20: 0.4 | F20: =B20 -> Qtr2 | G20: =C20 -> 644203.9 | H20: =D20 -> 0.4
B21: Qtr3 | C21: 719170.4 | D21: 0.41026549 | F21: =B21 -> Qtr3 | G21: =C21 -> 719170.4 | H21: =D21 -> 0.41026549
B22: Qtr4 | C22: 367582.1 | D22: 0.40243816 | F22: =B22 -> Qtr4 | G22: =C22 -> 367582.1 | H22: =D22 -> 0.40243816
A23: 2023 | B23: Qtr1 | C23: 1877584.3 | D23: 0.41657045 | E23: =A23 -> 2023 | F23: =B23 -> Qtr1 | G23: =C23 -> 1877584.3 | H23: =D23 -> 0.41657045
B24: Qtr2 | C24: 2379424.8 | D24: 0.42755819 | F24: =B24 -> Qtr2 | G24: =C24 -> 2379424.8 | H24: =D24 -> 0.42755819
B25: Qtr3 | C25: 2805752.5 | D25: 0.4347017 | F25: =B25 -> Qtr3 | G25: =C25 -> 2805752.5 | H25: =D25 -> 0.4347017
B26: Qtr4 | C26: 2530170.9 | D26: 0.42483933 | F26: =B26 -> Qtr4 | G26: =C26 -> 2530170.9 | H26: =D26 -> 0.42483933
A27: Grand Total | C27: 12016665 | D27: 0.42299129
A30: Sum of Total Sales | B30: Column Labels
A31: Row Labels | B31: 2022 | C31: 2023 | D31: Grand Total
A32: Amazon | B32: 276210 | C32: 1009698.7 | D32: 1285908.7
A33: BevCo | B33: 466788 | C33: 2327606.5 | D33: 2794394.5
A34: FizzyCo | B34: 161210.1 | C34: 2262827.1 | D34: 2424037.2
A35: Target | B35: 9250.3 | C35: 1341995 | D35: 1351245.3
A36: Walmart | B36: 339912.5 | C36: 580211 | D36: 920123.5
A37: West Soda | B37: 1170361.6 | C37: 2070594.2 | D37: 3240955.8
A38: Grand Total | B38: 2423732.5 | C38: 9592932.5 | D38: 12016665

Sheet Data
B2: Retailer Dataset
B4: Retailer | C4: Retailer ID | D4: Invoice Date | E4: Region | F4: State | G4: City | H4: Beverage Brand | I4: Price per Unit | J4: Units Sold | K4: Total Sales | L4: Operating Profit | M4: Operating Margin
B5: BevCo | C5: 1185732 | D5: 44562 | E5: Northeast | F5: New York | G5: New York | H5: Coca-Cola | I5: 0.5 | J5: 12000 | K5: 6000 | L5: 3000 | M5: 0.5
B6: BevCo | C6: 1185732 | D6: 44563 | E6: Northeast | F6: New York | G6: New York | H6: Diet Coke | I6: 0.5 | J6: 10000 | K6: 5000 | L6: 1500 | M6: 0.3
B7: BevCo | C7: 1185732 | D7: 44564 | E7: Northeast | F7: New York | G7: New York | H7: Sprite | I7: 0.4 | J7: 10000 | K7: 4000 | L7: 1400 | M7: 0.35
B8: BevCo | C8: 1185732 | D8: 44565 | E8: Northeast | F8: New York | G8: New York | H8: Fanta | I8: 0.45 | J8: 8500 | K8: 3825 | L8: 1338.75 | M8: 0.35
B9: BevCo | C9: 1185732 | D9: 44566 | E9: Northeast | F9: New York | G9: New York | H9: Powerade | I9: 0.6 | J9: 9000 | K9: 5400 | L9: 1620 | M9: 0.3
B10: BevCo | C10: 1185732 | D10: 44567 | E10: Northeast | F10: New York | G10: New York | H10: Dasani Water | I10: 0.5 | J10: 10000 | K10: 5000 | L10: 1250 | M10: 0.25
B11: BevCo | C11: 1185732 | D11: 44568 | E11: Northeast | F11: New York | G11: New York | H11: Coca-Cola | I11: 0.5 | J11: 12500 | K11: 6250 | L11: 3125 | M11: 0.5
B12: BevCo | C12: 1185732 | D12: 44569 | E12: Northeast | F12: New York | G12: New York | H12: Diet Coke | I12: 0.5 | J12: 9000 | K12: 4500 | L12: 1350 | M12: 0.3
B13: BevCo | C13: 1185732 | D13: 44582 | E13: Northeast | F13: New York | G13: New York | H13: Sprite | I13: 0.4 | J13: 9500 | K13: 3800 | L13: 1330 | M13: 0.35
B14: BevCo | C14: 1185732 | D14: 44583 | E14: Northeast | F14: New York | G14: New York | H14: Fanta | I14: 0.45 | J14: 8250 | K14: 3712.5 | L14: 1299.375 | M14: 0.35
B15: BevCo | C15: 1185732 | D15: 44584 | E15: Northeast | F15: New York | G15: New York | H15: Powerade | I15: 0.6 | J15: 9000 | K15: 5400 | L15: 1620 | M15: 0.3
B16: BevCo | C16: 1185732 | D16: 44585 | E16: Northeast | F16: New York | G16: New York | H16: Dasani Water | I16: 0.5 | J16: 10000 | K16: 5000 | L16: 1250 | M16: 0.25
... B9652: BevCo | C9652: 1185732 | D9652: 44979 | E9652: Northeast | F9652: New Hampshire | G9652: Manchester | H9652: Sprite | I9652: 0.29 | J9652: 830 | K9652: 240.7 | L9652: 64.989 | M9652: 0.27

Sheet Dashboard
C12: Sales by Beverage Brand | I12: Sales by Retailer
C13: Brand | D13: Sales2022 | E13: Sales2023 | F13: Variance | I13: Retailer | J13: Sales2022 | K13: Sales 2023 | L13: Variance
C14: =Analysis!A9 -> Coca-Cola | D14: =Analysis!B9 -> 499102 | E14: =Analysis!C9 -> 2268974.9 | F14: =E14-D14 -> 1769872.9 | I14: =Analysis!A32 -> Amazon | J14: =Analysis!B32 -> 276210 | K14: =Analysis!C32 -> 1009698.7 | L14: =Analysis!D32 -> 1285908.7
C15: =Analysis!A10 -> Dasani Water | D15: =Analysis!B10 -> 469270.7 | E15: =Analysis!C10 -> 1917827.8 | F15: =E15-D15 -> 1448557.1 | I15: =Analysis!A33 -> BevCo | J15: =Analysis!B33 -> 466788 | K15: =Analysis!C33 -> 2327606.5 | L15: =Analysis!D33 -> 2794394.5
C16: =Analysis!A11 -> Diet Coke | D16: =Analysis!B11 -> 423758.7 | E16: =Analysis!C11 -> 1633959.3 | F16: =E16-D16 -> 1210200.6 | I16: =Analysis!A34 -> FizzyCo | J16: =Analysis!B34 -> 161210.1 | K16: =Analysis!C34 -> 2262827.1 | L16: =Analysis!D34 -> 2424037.2
C17: =Analysis!A12 -> Fanta | D17: =Analysis!B12 -> 315489.2 | E17: =Analysis!C12 -> 1116062.9 | F17: =E17-D17 -> 800573.7 | I17: =Analysis!A35 -> Target | J17: =Analysis!B35 -> 9250.3 | K17: =Analysis!C35 -> 1341995 | L17: =Analysis!D35 -> 1351245.3
C18: =Analysis!A13 -> Powerade | D18: =Analysis!B13 -> 349533.9 | E18: =Analysis!C13 -> 1302529.3 | F18: =E18-D18 -> 952995.4 | I18: =Analysis!A36 -> Walmart | J18: =Analysis!B36 -> 339912.5 | K18: =Analysis!C36 -> 580211 | L18: =Analysis!D36 -> 920123.5
C19: =Analysis!A14 -> Sprite | D19: =Analysis!B14 -> 366578 | E19: =Analysis!C14 -> 1353578.3 | F19: =E19-D19 -> 987000.3 | I19: =Analysis!A37 -> West Soda | J19: =Analysis!B37 -> 1170361.6 | K19: =Analysis!C37 -> 2070594.2 | L19: =Analysis!D37 -> 3240955.8
C20: Total | D20: =Analysis!B15 -> 2423732.5 | E20: =Analysis!C15 -> 9592932.5 | F20: =E20-D20 -> 7169200 | I20: Total | J20: =Analysis!B38 -> 2423732.5 | K20: =Analysis!C38 -> 9592932.5 | L20: =Analysis!D38 -> 12016665
C25: Sales And operating Profit Margin by Quarter
